edzed/__init__.py
edzed/addons.py
edzed/block.py
edzed/demo.py
edzed/exceptions.py
edzed/fsm.py
edzed/simulator.py
edzed/blocklib/__init__.py
edzed/blocklib/cblocks.py
edzed/blocklib/cron.py
edzed/blocklib/filters.py
edzed/blocklib/fsms.py
edzed/blocklib/sblocks1.py
edzed/blocklib/sblocks2.py
edzed/blocklib/timedate.py
edzed/blocklib/timeinterval.py
edzed/utils/__init__.py
edzed/utils/flag.py
edzed/utils/looptimes.py
edzed/utils/shield_cancel.py
edzed/utils/shield_cancel_util.py
edzed/utils/tconst.py
edzed/utils/timeunits.py
edzed-26.1.2.dist-info/licenses/LICENSE.txt
edzed-26.1.2.dist-info/METADATA
edzed-26.1.2.dist-info/WHEEL
edzed-26.1.2.dist-info/top_level.txt
edzed-26.1.2.dist-info/RECORD
