Metadata-Version: 2.4
Name: edzed
Version: 26.1.2
Summary: An asyncio based library for building small automated systems
Author-email: Vlado Potisk <edzed@poti.sk>
License-Expression: MIT
Project-URL: homepage, https://github.com/xitop/edzed
Project-URL: repository, https://github.com/xitop/edzed
Project-URL: documentation, https://edzed.readthedocs.io/en/latest/
Keywords: automation,finite-state machine
Classifier: Development Status :: 6 - Mature
Classifier: Intended Audience :: Developers
Classifier: Topic :: Software Development :: Libraries :: Python Modules
Classifier: Programming Language :: Python :: 3
Requires-Python: >=3.9
License-File: LICENSE.txt
Provides-Extra: tests
Requires-Dist: pytest>=8.2.0; extra == "tests"
Requires-Dist: pytest-asyncio>=0.26.0; extra == "tests"
Requires-Dist: pytest-forked; extra == "tests"
Requires-Dist: pytest-xdist; extra == "tests"
Dynamic: license-file
